{
    "hyperparameters": {
        "learning_rate": 8.127468451585953e-06,
        "batch_size": 16,
        "weight_decay": 0.004872366381707842,
        "trainable_layers": 4,
        "dropout_rate": 0.19212405307715616,
        "optimizer": {
            "type": "SGD",
            "parameters": {
                "momentum": 0.9374368559450608
            }
        },
        "scheduler": {
            "type": "StepLR",
            "parameters": {
                "step_size": 4,
                "gamma": 0.582874947230325
            }
        },
        "label_smoothing": 0.021483506722757645
    },
    "train_metrics": [
        {
            "epoch": 1,
            "loss": 1.3540071091982693,
            "accuracy": 0.3522018706157444,
            "precision": 0.34798915020446053,
            "recall": 0.3522018706157443,
            "f1_score": 0.34167059770011876
        },
        {
            "epoch": 2,
            "loss": 1.2924570456576923,
            "accuracy": 0.47086905689789554,
            "precision": 0.46013139555339044,
            "recall": 0.4708690568978955,
            "f1_score": 0.4618867312920256
        },
        {
            "epoch": 3,
            "loss": 1.2353563095012496,
            "accuracy": 0.529423226812159,
            "precision": 0.517165089178386,
            "recall": 0.529423226812159,
            "f1_score": 0.5206194981256327
        },
        {
            "epoch": 4,
            "loss": 1.1774774781447876,
            "accuracy": 0.583008573655495,
            "precision": 0.5727222036775692,
            "recall": 0.583008573655495,
            "f1_score": 0.5733275336618625
        },
        {
            "epoch": 5,
            "loss": 1.1224030177294047,
            "accuracy": 0.6155494933749026,
            "precision": 0.6070090663857559,
            "recall": 0.6155494933749025,
            "f1_score": 0.6084621794748846
        },
        {
            "epoch": 6,
            "loss": 1.0715462815826606,
            "accuracy": 0.6484801247077163,
            "precision": 0.6414432586316644,
            "recall": 0.6484801247077162,
            "f1_score": 0.6430881228058025
        },
        {
            "epoch": 7,
            "loss": 1.0268065245562201,
            "accuracy": 0.666991426344505,
            "precision": 0.6603221318673358,
            "recall": 0.666991426344505,
            "f1_score": 0.66246301975485
        },
        {
            "epoch": 8,
            "loss": 0.9864919116881706,
            "accuracy": 0.6910561184723305,
            "precision": 0.6874330735191962,
            "recall": 0.6910561184723305,
            "f1_score": 0.687310193841481
        },
        {
            "epoch": 9,
            "loss": 0.9482718016705473,
            "accuracy": 0.7022603273577552,
            "precision": 0.6989455018330872,
            "recall": 0.7022603273577552,
            "f1_score": 0.6993153088239363
        }
    ],
    "val_metrics": [
        {
            "epoch": 1,
            "loss": 1.353084179360097,
            "accuracy": 0.4030511811023622,
            "precision": 0.4013503893119846,
            "recall": 0.4030511811023622,
            "f1_score": 0.3958518408620083
        },
        {
            "epoch": 2,
            "loss": 1.3190456281496783,
            "accuracy": 0.4325787401574803,
            "precision": 0.42658389760088444,
            "recall": 0.4325787401574803,
            "f1_score": 0.42233258089843617
        },
        {
            "epoch": 3,
            "loss": 1.3156339812466478,
            "accuracy": 0.3873031496062992,
            "precision": 0.4330715462338173,
            "recall": 0.38730314960629925,
            "f1_score": 0.4000897539040463
        },
        {
            "epoch": 4,
            "loss": 1.289662023228923,
            "accuracy": 0.42765748031496065,
            "precision": 0.44843260720322176,
            "recall": 0.4276574803149606,
            "f1_score": 0.4272404661410251
        },
        {
            "epoch": 5,
            "loss": 1.2899917880381186,
            "accuracy": 0.36023622047244097,
            "precision": 0.4324510542882982,
            "recall": 0.36023622047244097,
            "f1_score": 0.3797109983094845
        },
        {
            "epoch": 6,
            "loss": 1.2717488619286244,
            "accuracy": 0.38188976377952755,
            "precision": 0.43238112967884257,
            "recall": 0.38188976377952755,
            "f1_score": 0.39693266438832964
        },
        {
            "epoch": 7,
            "loss": 1.283851774658744,
            "accuracy": 0.3617125984251969,
            "precision": 0.45547926088561885,
            "recall": 0.3617125984251969,
            "f1_score": 0.37823113114654344
        },
        {
            "epoch": 8,
            "loss": 1.2676018898881327,
            "accuracy": 0.37401574803149606,
            "precision": 0.43081682936492344,
            "recall": 0.37401574803149606,
            "f1_score": 0.38620894575392584
        },
        {
            "epoch": 9,
            "loss": 1.2900718553798405,
            "accuracy": 0.3375984251968504,
            "precision": 0.42529082957659853,
            "recall": 0.3375984251968504,
            "f1_score": 0.35330723235408523
        }
    ],
    "classification_report": {
        "0": {
            "precision": 0.20405727923627684,
            "recall": 0.33661417322834647,
            "f1-score": 0.2540861812778603,
            "support": 508.0
        },
        "1": {
            "precision": 0.38727272727272727,
            "recall": 0.41929133858267714,
            "f1-score": 0.40264650283553877,
            "support": 508.0
        },
        "2": {
            "precision": 0.8211009174311926,
            "recall": 0.35236220472440943,
            "f1-score": 0.4931129476584022,
            "support": 508.0
        },
        "3": {
            "precision": 0.2887323943661972,
            "recall": 0.2421259842519685,
            "f1-score": 0.2633832976445396,
            "support": 508.0
        },
        "accuracy": 0.3375984251968504,
        "macro avg": {
            "precision": 0.42529082957659853,
            "recall": 0.3375984251968504,
            "f1-score": 0.35330723235408523,
            "support": 2032.0
        },
        "weighted avg": {
            "precision": 0.4252908295765984,
            "recall": 0.3375984251968504,
            "f1-score": 0.35330723235408523,
            "support": 2032.0
        }
    },
    "final_metrics": {
        "val_loss": 1.2900718553798405,
        "val_accuracy": 0.3375984251968504,
        "val_precision": 0.42529082957659853,
        "val_recall": 0.3375984251968504,
        "val_f1": 0.35330723235408523
    }
}