{
    "hyperparameters": {
        "learning_rate": 3.881722588025148e-06,
        "batch_size": 16,
        "weight_decay": 0.0011092557699080993,
        "trainable_layers": 4,
        "dropout_rate": 0.19960174225553506,
        "optimizer": {
            "type": "SGD",
            "parameters": {
                "momentum": 0.9424781050616929
            }
        },
        "scheduler": {
            "type": "StepLR",
            "parameters": {
                "step_size": 4,
                "gamma": 0.6331769394082714
            }
        },
        "label_smoothing": 0.0016290770787568067
    },
    "train_metrics": [
        {
            "epoch": 1,
            "loss": 1.3680680300793606,
            "accuracy": 0.31605611847233045,
            "precision": 0.3134079791749381,
            "recall": 0.3160561184723305,
            "f1_score": 0.3048667122346296
        },
        {
            "epoch": 2,
            "loss": 1.331636175826854,
            "accuracy": 0.4069563522992985,
            "precision": 0.40012901630046616,
            "recall": 0.4069563522992985,
            "f1_score": 0.39867983399706364
        },
        {
            "epoch": 3,
            "loss": 1.2986026715228822,
            "accuracy": 0.45576773187840997,
            "precision": 0.4444916072643707,
            "recall": 0.45576773187840997,
            "f1_score": 0.4470198123037677
        },
        {
            "epoch": 4,
            "loss": 1.2650329838111265,
            "accuracy": 0.49824629773967266,
            "precision": 0.48649852659033993,
            "recall": 0.49824629773967266,
            "f1_score": 0.48789262953350165
        },
        {
            "epoch": 5,
            "loss": 1.233734967833093,
            "accuracy": 0.5273772408417771,
            "precision": 0.5168967225236726,
            "recall": 0.5273772408417771,
            "f1_score": 0.5183065371324498
        },
        {
            "epoch": 6,
            "loss": 1.2026116322095934,
            "accuracy": 0.5547544816835541,
            "precision": 0.5439852258719243,
            "recall": 0.5547544816835542,
            "f1_score": 0.546105971725295
        },
        {
            "epoch": 7,
            "loss": 1.171744461832619,
            "accuracy": 0.5773577552611068,
            "precision": 0.5670170200875781,
            "recall": 0.5773577552611068,
            "f1_score": 0.5691549161131925
        },
        {
            "epoch": 8,
            "loss": 1.1431089213186192,
            "accuracy": 0.5999610288386594,
            "precision": 0.5904894915313497,
            "recall": 0.5999610288386593,
            "f1_score": 0.5919652292033679
        },
        {
            "epoch": 9,
            "loss": 1.112002423194267,
            "accuracy": 0.6171083398285269,
            "precision": 0.6080993545328786,
            "recall": 0.6171083398285269,
            "f1_score": 0.6100023557418783
        }
    ],
    "val_metrics": [
        {
            "epoch": 1,
            "loss": 1.3629543649868703,
            "accuracy": 0.38631889763779526,
            "precision": 0.37743243016635536,
            "recall": 0.38631889763779526,
            "f1_score": 0.36672871793760575
        },
        {
            "epoch": 2,
            "loss": 1.3371268426339458,
            "accuracy": 0.4256889763779528,
            "precision": 0.4070812950956284,
            "recall": 0.4256889763779527,
            "f1_score": 0.4072556589705211
        },
        {
            "epoch": 3,
            "loss": 1.3371956076209002,
            "accuracy": 0.4124015748031496,
            "precision": 0.4241177807970318,
            "recall": 0.4124015748031496,
            "f1_score": 0.4095979908348199
        },
        {
            "epoch": 4,
            "loss": 1.3181321977630376,
            "accuracy": 0.4424212598425197,
            "precision": 0.4267195403120191,
            "recall": 0.4424212598425197,
            "f1_score": 0.41964303806722203
        },
        {
            "epoch": 5,
            "loss": 1.3163071016627035,
            "accuracy": 0.38188976377952755,
            "precision": 0.41854720144735885,
            "recall": 0.3818897637795276,
            "f1_score": 0.3919108629456485
        },
        {
            "epoch": 6,
            "loss": 1.2981179680411272,
            "accuracy": 0.4197834645669291,
            "precision": 0.4171724780864144,
            "recall": 0.41978346456692917,
            "f1_score": 0.416642319673974
        },
        {
            "epoch": 7,
            "loss": 1.2967276169559148,
            "accuracy": 0.391240157480315,
            "precision": 0.43247403222726966,
            "recall": 0.391240157480315,
            "f1_score": 0.40595772564116306
        },
        {
            "epoch": 8,
            "loss": 1.282828417349988,
            "accuracy": 0.391240157480315,
            "precision": 0.4141381692379828,
            "recall": 0.39124015748031493,
            "f1_score": 0.40083264567732174
        },
        {
            "epoch": 9,
            "loss": 1.2813753903381468,
            "accuracy": 0.3631889763779528,
            "precision": 0.41097683854534206,
            "recall": 0.3631889763779528,
            "f1_score": 0.3790471444089516
        }
    ],
    "classification_report": {
        "0": {
            "precision": 0.1905972045743329,
            "recall": 0.2952755905511811,
            "f1-score": 0.23166023166023167,
            "support": 508.0
        },
        "1": {
            "precision": 0.32972972972972975,
            "recall": 0.24015748031496062,
            "f1-score": 0.27790432801822323,
            "support": 508.0
        },
        "2": {
            "precision": 0.7963446475195822,
            "recall": 0.6003937007874016,
            "f1-score": 0.6846240179573513,
            "support": 508.0
        },
        "3": {
            "precision": 0.32723577235772355,
            "recall": 0.3169291338582677,
            "f1-score": 0.322,
            "support": 508.0
        },
        "accuracy": 0.3631889763779528,
        "macro avg": {
            "precision": 0.41097683854534206,
            "recall": 0.3631889763779528,
            "f1-score": 0.3790471444089516,
            "support": 2032.0
        },
        "weighted avg": {
            "precision": 0.41097683854534217,
            "recall": 0.3631889763779528,
            "f1-score": 0.37904714440895154,
            "support": 2032.0
        }
    },
    "final_metrics": {
        "val_loss": 1.2813753903381468,
        "val_accuracy": 0.3631889763779528,
        "val_precision": 0.41097683854534206,
        "val_recall": 0.3631889763779528,
        "val_f1": 0.3790471444089516
    }
}